I2OI.v
/** FETCH	**/
module Fetch 
(	
	input zero, rst, clk, branch, 
	input [31:0] branch_res, 
	
	output [31:0] inst
);

	wire [31:0] PC, PC_4, newPC;

	assign PC_4 = PC + 4; // pc+4  Adder
	assign newPC = (branch & zero) ? PC_4 + branch_res : PC_4; // desvia se for um branch beq for true

	PC program_counter(newPC, clk, rst, PC);

	reg [31:0] inst_mem [0:31];

	assign inst = inst_mem[PC[31:2]];

	initial
	begin
		// Exemplos
		inst_mem[0] <= 32'h00000000; // nop
		inst_mem[1] <= 32'h00500113; // addi x2, x0, 5  ok
		inst_mem[2] <= 32'h00210233; // add  x4, x2, x2  ok
		//inst_mem[1] <= 32'h00202223; // sw x2, 8(x0) ok
		//inst_mem[1] <= 32'h0050a423; // sw x5, 8(x1) ok
		//inst_mem[2] <= 32'h0000a003; // lw x1, x0(0) ok
		//inst_mem[1] <= 32'hfff00113; // addi x2,x0,-1 ok
		//inst_mem[2] <= 32'h00318133; // add x2, x3, x3 ok
		//inst_mem[3] <= 32'h40328133; // sub x2, x5, x3 ok
	end

endmodule



module PC 
(
	input [31:0] pc_in, 
	input clk, rst, 
	
	output reg [31:0] pc_out
);

	always @(posedge clk) 
	begin
		pc_out <= pc_in;
		if (~rst)
			pc_out <= 0;
	end

endmodule



/** DECODE **/
module Decode 
(
	input [31:0] inst, writedata, 
	input clk, 

	output [31:0] data1, data2, ImmGen, 
	output alusrc, memread, memwrite, memtoreg, branch, 
	output [1:0] aluop, 
	output [9:0] funct
);

	wire branch, memread, memtoreg, MemWrite, alusrc, regwrite;
	wire [1:0] aluop; 
	wire [4:0] writereg, rs1, rs2, rd;
	wire [6:0] opcode;
	wire [9:0] funct;
	wire [31:0] ImmGen;

	assign opcode = inst[6:0];
	assign rs1    = inst[19:15];
	assign rs2    = inst[24:20];
	assign rd     = inst[11:7];
	assign funct = {inst[31:25],inst[14:12]};

	Controle control (opcode, inst, alusrc, memtoreg, regwrite, memread, memwrite, branch, aluop, ImmGen);

	ARF registradores (clk, regwrite, rs1, rs2, rd, writedata, data1, data2); 

endmodule




/** ISSUE **/

module Issue();

endmodule


module Score_Board();

endmodule





/** EXECUTE **/
module Execute 
(
	input [31:0] in1, in2, ImmGen, 
	input alusrc, input [1:0] aluop, 
	input [9:0] funct, 
	
	output zero, 
	output [31:0] aluout
);

  wire [31:0] alu_B;
  wire [3:0] aluctrl;
  
  assign alu_B = (alusrc) ? ImmGen : in2 ;

  //Unidade Lógico Aritimética
  ALU alu (aluctrl, in1, alu_B, aluout, zero);

  ALUcontrol alucontrol (aluop, funct, aluctrl);

endmodule


module ALU (input [3:0] alucontrol, input [31:0] A, B, output reg [31:0] aluout, output zero);
  
  assign zero = (aluout == 0); // Zero recebe um valor lógico caso aluout seja igual a zero.
  
  always @(alucontrol, A, B) begin
      case (alucontrol)
        0: aluout <= A & B; // AND
        1: aluout <= A | B; // OR
        2: aluout <= A + B; // ADD
        6: aluout <= A - B; // SUB
        //7: aluout <= A < B ? 32'd1:32'd0; //SLT
        //12: aluout <= ~(A | B); // NOR
      default: aluout <= 0; //default 0, Nada acontece;
    endcase
  end
endmodule

module Load_Store 
(
	input [31:0] address, writedata, 
	input memread, memwrite, clk, 
	
	output [31:0] readdata
);

  integer i;
  reg [31:0] memory [0:127]; 
  
  // fill the memory
  initial begin
    for (i = 0; i < 128; i=i+1) 
      memory[i] <= i;
  end

  assign readdata = (memread) ? memory[address[31:2]] : 0;

  always @(posedge clk) begin
    if (memwrite)
      memory[address[31:2]] <= writedata;
	end
endmodule


/** WRITEBACK **/
module Writeback 
(
	input [31:0] aluout, readdata, 
	input memtoreg, 
	
	output reg [31:0] write_data
);

	always @(memtoreg) begin
		write_data <= (memtoreg) ? readdata : aluout;
	end
endmodule

module Phisical_Register_file();

endmodule


module Reorder_Buffer();

endmodule


module Finished_Store_Buffer();


endmodule


/** COMMIT **/

module Commit();

endmodule


module ARF 
(
	input clk, regwrite, 
	input [4:0] read_reg1, read_reg2, writereg, 
	input [31:0] writedata, 
	
	output [31:0] read_data1, read_data2
);

	integer i;
	reg [31:0] memory [0:31]; // 32 registers de 32 bits cada

	// fill the memory
	initial 
	begin
		for (i = 0; i <= 31; i=i+1) 
			memory[i] <= i;
	end

	assign read_data1 = (regwrite && read_reg1==writereg) ? writedata : memory[read_reg1];
	assign read_data2 = (regwrite && read_reg2==writereg) ? writedata : memory[read_reg2];

	always @(posedge clk) 
	begin
		if (regwrite)
			memory[writereg] <= writedata;
	end

endmodule


/** CONTROL **/
module Controle 
(
	input [6:0] opcode, 
	input [31:0] inst, 

	output reg alusrc, memtoreg, regwrite, memread, memwrite, branch, 
	output reg [1:0] aluop, 
	output reg [31:0] ImmGen
);

  always @(opcode) begin
	alusrc   <= 0;
    memtoreg <= 0;
    regwrite <= 0;
    memread  <= 0;
    memwrite <= 0;
    branch   <= 0;
    aluop    <= 0;
    ImmGen   <= 0; 
    case(opcode) 
      7'b0110011: begin // R type == 51
        regwrite <= 1;
        aluop    <= 2;
			end
		  7'b1100011: begin // beq == 99
        branch   <= 1;
        aluop    <= 1;
        ImmGen   <= {{19{inst[31]}},inst[31],inst[7],inst[30:25],inst[11:8],1'b0};
			end
			7'b0010011: begin // addi == 19
        alusrc   <= 1;
        regwrite <= 1;
        ImmGen   <= {{20{inst[31]}},inst[31:20]};
      end
			7'b0000011: begin // lw == 3
        alusrc   <= 1;
        memtoreg <= 1;
        regwrite <= 1;
        memread  <= 1;
        ImmGen   <= {{20{inst[31]}},inst[31:20]};
      end
			7'b0100011: begin // sw == 35
        alusrc   <= 1;
        memwrite <= 1;
        ImmGen   <= {{20{inst[31]}},inst[31:25],inst[11:7]};
      end
    endcase
  end

endmodule 

module ALUcontrol (input [1:0] aluop, input [9:0] funct, output reg [3:0] alucontrol);
  
  wire [7:0] funct7;
  wire [2:0] funct3;

  assign funct3 = funct[2:0];
  assign funct7 = funct[9:3];

  always @(aluop) begin
    case (aluop)
      0: alucontrol <= 4'd2; // ADD to SW and LW
      1: alucontrol <= 4'd6; // SUB to branch
      default: begin
        case (funct3)
          0: alucontrol <= (funct7 == 0) ? /*ADD*/ 4'd2 : /*SUB*/ 4'd6; 
          2: alucontrol <= 4'd7; // SLT
          6: alucontrol <= 4'd1; // OR
          //39: alucontrol <= 4'd12; // NOR
          7: alucontrol <= 4'd0; // AND
          default: alucontrol <= 4'd15; // Nop
        endcase
      end
    endcase
  end
endmodule


/** CORE **/
module Core 
(
	input clk, rst, 
	
	output [31:0] writedata
);
  
  wire [31:0] inst, sigext, data1, data2, aluout, readdata;
  wire zero, memread, memwrite, memtoreg, branch, alusrc;
  wire [9:0] funct;
  wire [1:0] aluop;
  
  // FETCH STAGE
  Fetch fetch (zero, rst, clk, branch, sigext, inst);
  
  // DECODE STAGE
  Decode decode (inst, writedata, clk, data1, data2, sigext, alusrc, memread, memwrite, memtoreg, branch, aluop, funct);   
  
  // EXECUTE STAGE
  Execute execute (data1, data2, sigext, alusrc, aluop, funct, zero, aluout);

  // MEMORY STAGE
  Load_Store memory (aluout, data2, memread, memwrite, clk, readdata);

  // WRITEBACK STAGE
  Writeback writeback (aluout, readdata, memtoreg, writedata);
  
  
  
  
  

endmodule

TBs/tb.v
module tb();

	reg clk, rst;
	wire [31:0] saida;
	
	initial
	begin
		#0 clk <= 0; rst <= 0;
		#1 rst <= 1;
	end
	
	always #1 clk = ~clk;
	
	Core core(clk, rst, saida);

	initial 
	begin
        $dumpfile("dump.vcd"); //gerar arquivo de forma de onda, para ser usado no gtkwave
        $dumpvars(0,tb);
        
        $monitor("saida: %b", saida);
		
		#1000 $finish;
    end
    

endmodule

TBs/dump.vcd
$date
	Tue Oct  6 22:42:57 2020
$end
$version
	Icarus Verilog
$end
$timescale
	1s
$end
$scope module tb $end
$var wire 32 ! saida [31:0] $end
$var reg 1 " clk $end
$var reg 1 # rst $end
$scope module core $end
$var wire 2 $ aluop [1:0] $end
$var wire 32 % aluout [31:0] $end
$var wire 1 & alusrc $end
$var wire 1 ' branch $end
$var wire 1 ( clk $end
$var wire 32 ) data1 [31:0] $end
$var wire 32 * data2 [31:0] $end
$var wire 10 + funct [9:0] $end
$var wire 32 , inst [31:0] $end
$var wire 1 - memread $end
$var wire 1 . memtoreg $end
$var wire 1 / memwrite $end
$var wire 32 0 readdata [31:0] $end
$var wire 1 1 rst $end
$var wire 32 2 sigext [31:0] $end
$var wire 32 3 writedata [31:0] $end
$var wire 1 4 zero $end
$scope module fetch $end
$var wire 32 5 PC [31:0] $end
$var wire 32 6 PC_4 [31:0] $end
$var wire 1 ' branch $end
$var wire 32 7 branch_res [31:0] $end
$var wire 1 ( clk $end
$var wire 32 8 inst [31:0] $end
$var wire 32 9 newPC [31:0] $end
$var wire 1 1 rst $end
$var wire 1 4 zero $end
$scope module program_counter $end
$var wire 1 ( clk $end
$var wire 32 : pc_in [31:0] $end
$var wire 1 1 rst $end
$var reg 32 ; pc_out [31:0] $end
$upscope $end
$upscope $end
$scope module decode $end
$var wire 32 < ImmGen [31:0] $end
$var wire 2 = aluop [1:0] $end
$var wire 1 & alusrc $end
$var wire 1 ' branch $end
$var wire 1 ( clk $end
$var wire 32 > data1 [31:0] $end
$var wire 32 ? data2 [31:0] $end
$var wire 10 @ funct [9:0] $end
$var wire 32 A inst [31:0] $end
$var wire 1 - memread $end
$var wire 1 . memtoreg $end
$var wire 1 / memwrite $end
$var wire 7 B opcode [6:0] $end
$var wire 5 C rd [4:0] $end
$var wire 1 D regwrite $end
$var wire 5 E rs1 [4:0] $end
$var wire 5 F rs2 [4:0] $end
$var wire 32 G writedata [31:0] $end
$scope module control $end
$var wire 32 H inst [31:0] $end
$var wire 7 I opcode [6:0] $end
$var reg 32 J ImmGen [31:0] $end
$var reg 2 K aluop [1:0] $end
$var reg 1 L alusrc $end
$var reg 1 M branch $end
$var reg 1 N memread $end
$var reg 1 O memtoreg $end
$var reg 1 P memwrite $end
$var reg 1 Q regwrite $end
$upscope $end
$scope module registradores $end
$var wire 1 ( clk $end
$var wire 32 R read_data1 [31:0] $end
$var wire 32 S read_data2 [31:0] $end
$var wire 5 T read_reg1 [4:0] $end
$var wire 5 U read_reg2 [4:0] $end
$var wire 1 D regwrite $end
$var wire 32 V writedata [31:0] $end
$var wire 5 W writereg [4:0] $end
$var integer 32 X i [31:0] $end
$upscope $end
$upscope $end
$scope module execute $end
$var wire 32 Y ImmGen [31:0] $end
$var wire 32 Z alu_B [31:0] $end
$var wire 4 [ aluctrl [3:0] $end
$var wire 2 \ aluop [1:0] $end
$var wire 32 ] aluout [31:0] $end
$var wire 1 & alusrc $end
$var wire 10 ^ funct [9:0] $end
$var wire 32 _ in1 [31:0] $end
$var wire 32 ` in2 [31:0] $end
$var wire 1 4 zero $end
$scope module alu $end
$var wire 32 a A [31:0] $end
$var wire 32 b B [31:0] $end
$var wire 4 c alucontrol [3:0] $end
$var wire 1 4 zero $end
$var reg 32 d aluout [31:0] $end
$upscope $end
$scope module alucontrol $end
$var wire 2 e aluop [1:0] $end
$var wire 10 f funct [9:0] $end
$var wire 3 g funct3 [2:0] $end
$var wire 8 h funct7 [7:0] $end
$var reg 4 i alucontrol [3:0] $end
$upscope $end
$upscope $end
$scope module memory $end
$var wire 32 j address [31:0] $end
$var wire 1 ( clk $end
$var wire 1 - memread $end
$var wire 1 / memwrite $end
$var wire 32 k readdata [31:0] $end
$var wire 32 l writedata [31:0] $end
$var integer 32 m i [31:0] $end
$upscope $end
$scope module writeback $end
$var wire 32 n aluout [31:0] $end
$var wire 1 . memtoreg $end
$var wire 32 o readdata [31:0] $end
$var reg 32 p write_data [31:0] $end
$upscope $end
$upscope $end
$upscope $end
$enddefinitions $end
#0
$dumpvars
b0 p
b0 o
bx n
b10000000 m
bx l
b0 k
bx j
b10 i
b0xxxxxxx h
bx g
bx f
b0 e
bx d
b10 c
bx b
bx a
bx `
bx _
bx ^
bx ]
b0 \
b10 [
bx Z
b0 Y
b100000 X
bx W
b0 V
bx U
bx T
bx S
bx R
0Q
0P
0O
0N
0M
0L
b0 K
b0 J
bx I
bx H
b0 G
bx F
bx E
0D
bx C
bx B
bx A
bx @
bx ?
bx >
b0 =
b0 <
bx ;
bx :
bx 9
bx 8
b0 7
bx 6
bx 5
x4
b0 3
b0 2
01
b0 0
0/
0.
0-
bx ,
bx +
bx *
bx )
0(
0'
0&
bx %
b0 $
0#
0"
b0 !
$end
#1
b0 d
14
b0 %
b0 ]
b0 j
b0 n
b0 Z
b0 b
b0 )
b0 >
b0 R
b0 _
b0 a
b0 *
b0 ?
b0 S
b0 `
b0 l
b0 h
b0 g
b0 B
b0 I
b0 E
b0 T
b0 F
b0 U
b0 C
b0 W
b0 +
b0 @
b0 ^
b0 f
b100 9
b100 :
b0 ,
b0 8
b0 A
b0 H
b100 6
b0 ;
b0 5
1#
11
1"
1(
#2
0"
0(
#3
b101 d
04
b101 %
b101 ]
b101 j
b101 n
b101 J
b101 2
b101 7
b101 <
b101 Y
1Q
1D
1L
1&
b101 Z
b101 b
b101 *
b101 ?
b101 S
b101 `
b101 l
b10011 B
b10011 I
b101 F
b101 U
b10 C
b10 W
b1000 9
b1000 :
b10100000000000100010011 ,
b10100000000000100010011 8
b10100000000000100010011 A
b10100000000000100010011 H
b1000 6
b100 ;
b100 5
1"
1(
#4
0"
0(
#5
b0 d
14
b0 %
b0 ]
b0 j
b0 n
b0 Z
b0 b
b10 K
b10 $
b10 =
b10 \
b10 e
b0 J
b0 2
b0 7
b0 <
b0 Y
1Q
1D
0L
0&
b0 *
b0 ?
b0 S
b0 `
b0 l
b110011 B
b110011 I
b10 E
b10 T
b10 F
b10 U
b100 C
b100 W
b1100 9
b1100 :
b1000010000001000110011 ,
b1000010000001000110011 8
b1000010000001000110011 A
b1000010000001000110011 H
b1100 6
b1000 ;
b1000 5
1"
1(
#6
0"
0(
#7
bx d
x4
bx %
bx ]
bx j
bx n
b0 K
b0 $
b0 =
b0 \
b0 e
0Q
0D
bx Z
bx b
bx )
bx >
bx R
bx _
bx a
bx *
bx ?
bx S
bx `
bx l
b0xxxxxxx h
bx g
bx B
bx I
bx E
bx T
bx F
bx U
bx C
bx W
bx +
bx @
bx ^
bx f
b10000 9
b10000 :
bx ,
bx 8
bx A
bx H
b10000 6
b1100 ;
b1100 5
1"
1(
#8
0"
0(
#9
b10100 9
b10100 :
b10100 6
b10000 ;
b10000 5
1"
1(
#10
0"
0(
#11
b11000 9
b11000 :
b11000 6
b10100 ;
b10100 5
1"
1(
#12
0"
0(
#13
b11100 9
b11100 :
b11100 6
b11000 ;
b11000 5
1"
1(
#14
0"
0(
#15
b100000 9
b100000 :
b100000 6
b11100 ;
b11100 5
1"
1(
#16
0"
0(
#17
b100100 9
b100100 :
b100100 6
b100000 ;
b100000 5
1"
1(
#18
0"
0(
#19
b101000 9
b101000 :
b101000 6
b100100 ;
b100100 5
1"
1(
#20
0"
0(
#21
b101100 9
b101100 :
b101100 6
b101000 ;
b101000 5
1"
1(
#22
0"
0(
#23
b110000 9
b110000 :
b110000 6
b101100 ;
b101100 5
1"
1(
#24
0"
0(
#25
b110100 9
b110100 :
b110100 6
b110000 ;
b110000 5
1"
1(
#26
0"
0(
#27
b111000 9
b111000 :
b111000 6
b110100 ;
b110100 5
1"
1(
#28
0"
0(
#29
b111100 9
b111100 :
b111100 6
b111000 ;
b111000 5
1"
1(
#30
0"
0(
#31
b1000000 9
b1000000 :
b1000000 6
b111100 ;
b111100 5
1"
1(
#32
0"
0(
#33
b1000100 9
b1000100 :
b1000100 6
b1000000 ;
b1000000 5
1"
1(
#34
0"
0(
#35
b1001000 9
b1001000 :
b1001000 6
b1000100 ;
b1000100 5
1"
1(
#36
0"
0(
#37
b1001100 9
b1001100 :
b1001100 6
b1001000 ;
b1001000 5
1"
1(
#38
0"
0(
#39
b1010000 9
b1010000 :
b1010000 6
b1001100 ;
b1001100 5
1"
1(
#40
0"
0(
#41
b1010100 9
b1010100 :
b1010100 6
b1010000 ;
b1010000 5
1"
1(
#42
0"
0(
#43
b1011000 9
b1011000 :
b1011000 6
b1010100 ;
b1010100 5
1"
1(
#44
0"
0(
#45
b1011100 9
b1011100 :
b1011100 6
b1011000 ;
b1011000 5
1"
1(
#46
0"
0(
#47
b1100000 9
b1100000 :
b1100000 6
b1011100 ;
b1011100 5
1"
1(
#48
0"
0(
#49
b1100100 9
b1100100 :
b1100100 6
b1100000 ;
b1100000 5
1"
1(
#50
0"
0(
#51
b1101000 9
b1101000 :
b1101000 6
b1100100 ;
b1100100 5
1"
1(
#52
0"
0(
#53
b1101100 9
b1101100 :
b1101100 6
b1101000 ;
b1101000 5
1"
1(
#54
0"
0(
#55
b1110000 9
b1110000 :
b1110000 6
b1101100 ;
b1101100 5
1"
1(
#56
0"
0(
#57
b1110100 9
b1110100 :
b1110100 6
b1110000 ;
b1110000 5
1"
1(
#58
0"
0(
#59
b1111000 9
b1111000 :
b1111000 6
b1110100 ;
b1110100 5
1"
1(
#60
0"
0(
#61
b1111100 9
b1111100 :
b1111100 6
b1111000 ;
b1111000 5
1"
1(
#62
0"
0(
#63
b10000000 9
b10000000 :
b10000000 6
b1111100 ;
b1111100 5
1"
1(
#64
0"
0(
#65
b10000100 9
b10000100 :
b10000100 6
b10000000 ;
b10000000 5
1"
1(
#66
0"
0(
#67
b10001000 9
b10001000 :
b10001000 6
b10000100 ;
b10000100 5
1"
1(
#68
0"
0(
#69
b10001100 9
b10001100 :
b10001100 6
b10001000 ;
b10001000 5
1"
1(
#70
0"
0(
#71
b10010000 9
b10010000 :
b10010000 6
b10001100 ;
b10001100 5
1"
1(
#72
0"
0(
#73
b10010100 9
b10010100 :
b10010100 6
b10010000 ;
b10010000 5
1"
1(
#74
0"
0(
#75
b10011000 9
b10011000 :
b10011000 6
b10010100 ;
b10010100 5
1"
1(
#76
0"
0(
#77
b10011100 9
b10011100 :
b10011100 6
b10011000 ;
b10011000 5
1"
1(
#78
0"
0(
#79
b10100000 9
b10100000 :
b10100000 6
b10011100 ;
b10011100 5
1"
1(
#80
0"
0(
#81
b10100100 9
b10100100 :
b10100100 6
b10100000 ;
b10100000 5
1"
1(
#82
0"
0(
#83
b10101000 9
b10101000 :
b10101000 6
b10100100 ;
b10100100 5
1"
1(
#84
0"
0(
#85
b10101100 9
b10101100 :
b10101100 6
b10101000 ;
b10101000 5
1"
1(
#86
0"
0(
#87
b10110000 9
b10110000 :
b10110000 6
b10101100 ;
b10101100 5
1"
1(
#88
0"
0(
#89
b10110100 9
b10110100 :
b10110100 6
b10110000 ;
b10110000 5
1"
1(
#90
0"
0(
#91
b10111000 9
b10111000 :
b10111000 6
b10110100 ;
b10110100 5
1"
1(
#92
0"
0(
#93
b10111100 9
b10111100 :
b10111100 6
b10111000 ;
b10111000 5
1"
1(
#94
0"
0(
#95
b11000000 9
b11000000 :
b11000000 6
b10111100 ;
b10111100 5
1"
1(
#96
0"
0(
#97
b11000100 9
b11000100 :
b11000100 6
b11000000 ;
b11000000 5
1"
1(
#98
0"
0(
#99
b11001000 9
b11001000 :
b11001000 6
b11000100 ;
b11000100 5
1"
1(
#100
0"
0(
#101
b11001100 9
b11001100 :
b11001100 6
b11001000 ;
b11001000 5
1"
1(
#102
0"
0(
#103
b11010000 9
b11010000 :
b11010000 6
b11001100 ;
b11001100 5
1"
1(
#104
0"
0(
#105
b11010100 9
b11010100 :
b11010100 6
b11010000 ;
b11010000 5
1"
1(
#106
0"
0(
#107
b11011000 9
b11011000 :
b11011000 6
b11010100 ;
b11010100 5
1"
1(
#108
0"
0(
#109
b11011100 9
b11011100 :
b11011100 6
b11011000 ;
b11011000 5
1"
1(
#110
0"
0(
#111
b11100000 9
b11100000 :
b11100000 6
b11011100 ;
b11011100 5
1"
1(
#112
0"
0(
#113
b11100100 9
b11100100 :
b11100100 6
b11100000 ;
b11100000 5
1"
1(
#114
0"
0(
#115
b11101000 9
b11101000 :
b11101000 6
b11100100 ;
b11100100 5
1"
1(
#116
0"
0(
#117
b11101100 9
b11101100 :
b11101100 6
b11101000 ;
b11101000 5
1"
1(
#118
0"
0(
#119
b11110000 9
b11110000 :
b11110000 6
b11101100 ;
b11101100 5
1"
1(
#120
0"
0(
#121
b11110100 9
b11110100 :
b11110100 6
b11110000 ;
b11110000 5
1"
1(
#122
0"
0(
#123
b11111000 9
b11111000 :
b11111000 6
b11110100 ;
b11110100 5
1"
1(
#124
0"
0(
#125
b11111100 9
b11111100 :
b11111100 6
b11111000 ;
b11111000 5
1"
1(
#126
0"
0(
#127
b100000000 9
b100000000 :
b100000000 6
b11111100 ;
b11111100 5
1"
1(
#128
0"
0(
#129
b100000100 9
b100000100 :
b100000100 6
b100000000 ;
b100000000 5
1"
1(
#130
0"
0(
#131
b100001000 9
b100001000 :
b100001000 6
b100000100 ;
b100000100 5
1"
1(
#132
0"
0(
#133
b100001100 9
b100001100 :
b100001100 6
b100001000 ;
b100001000 5
1"
1(
#134
0"
0(
#135
b100010000 9
b100010000 :
b100010000 6
b100001100 ;
b100001100 5
1"
1(
#136
0"
0(
#137
b100010100 9
b100010100 :
b100010100 6
b100010000 ;
b100010000 5
1"
1(
#138
0"
0(
#139
b100011000 9
b100011000 :
b100011000 6
b100010100 ;
b100010100 5
1"
1(
#140
0"
0(
#141
b100011100 9
b100011100 :
b100011100 6
b100011000 ;
b100011000 5
1"
1(
#142
0"
0(
#143
b100100000 9
b100100000 :
b100100000 6
b100011100 ;
b100011100 5
1"
1(
#144
0"
0(
#145
b100100100 9
b100100100 :
b100100100 6
b100100000 ;
b100100000 5
1"
1(
#146
0"
0(
#147
b100101000 9
b100101000 :
b100101000 6
b100100100 ;
b100100100 5
1"
1(
#148
0"
0(
#149
b100101100 9
b100101100 :
b100101100 6
b100101000 ;
b100101000 5
1"
1(
#150
0"
0(
#151
b100110000 9
b100110000 :
b100110000 6
b100101100 ;
b100101100 5
1"
1(
#152
0"
0(
#153
b100110100 9
b100110100 :
b100110100 6
b100110000 ;
b100110000 5
1"
1(
#154
0"
0(
#155
b100111000 9
b100111000 :
b100111000 6
b100110100 ;
b100110100 5
1"
1(
#156
0"
0(
#157
b100111100 9
b100111100 :
b100111100 6
b100111000 ;
b100111000 5
1"
1(
#158
0"
0(
#159
b101000000 9
b101000000 :
b101000000 6
b100111100 ;
b100111100 5
1"
1(
#160
0"
0(
#161
b101000100 9
b101000100 :
b101000100 6
b101000000 ;
b101000000 5
1"
1(
#162
0"
0(
#163
b101001000 9
b101001000 :
b101001000 6
b101000100 ;
b101000100 5
1"
1(
#164
0"
0(
#165
b101001100 9
b101001100 :
b101001100 6
b101001000 ;
b101001000 5
1"
1(
#166
0"
0(
#167
b101010000 9
b101010000 :
b101010000 6
b101001100 ;
b101001100 5
1"
1(
#168
0"
0(
#169
b101010100 9
b101010100 :
b101010100 6
b101010000 ;
b101010000 5
1"
1(
#170
0"
0(
#171
b101011000 9
b101011000 :
b101011000 6
b101010100 ;
b101010100 5
1"
1(
#172
0"
0(
#173
b101011100 9
b101011100 :
b101011100 6
b101011000 ;
b101011000 5
1"
1(
#174
0"
0(
#175
b101100000 9
b101100000 :
b101100000 6
b101011100 ;
b101011100 5
1"
1(
#176
0"
0(
#177
b101100100 9
b101100100 :
b101100100 6
b101100000 ;
b101100000 5
1"
1(
#178
0"
0(
#179
b101101000 9
b101101000 :
b101101000 6
b101100100 ;
b101100100 5
1"
1(
#180
0"
0(
#181
b101101100 9
b101101100 :
b101101100 6
b101101000 ;
b101101000 5
1"
1(
#182
0"
0(
#183
b101110000 9
b101110000 :
b101110000 6
b101101100 ;
b101101100 5
1"
1(
#184
0"
0(
#185
b101110100 9
b101110100 :
b101110100 6
b101110000 ;
b101110000 5
1"
1(
#186
0"
0(
#187
b101111000 9
b101111000 :
b101111000 6
b101110100 ;
b101110100 5
1"
1(
#188
0"
0(
#189
b101111100 9
b101111100 :
b101111100 6
b101111000 ;
b101111000 5
1"
1(
#190
0"
0(
#191
b110000000 9
b110000000 :
b110000000 6
b101111100 ;
b101111100 5
1"
1(
#192
0"
0(
#193
b110000100 9
b110000100 :
b110000100 6
b110000000 ;
b110000000 5
1"
1(
#194
0"
0(
#195
b110001000 9
b110001000 :
b110001000 6
b110000100 ;
b110000100 5
1"
1(
#196
0"
0(
#197
b110001100 9
b110001100 :
b110001100 6
b110001000 ;
b110001000 5
1"
1(
#198
0"
0(
#199
b110010000 9
b110010000 :
b110010000 6
b110001100 ;
b110001100 5
1"
1(
#200
0"
0(
#201
b110010100 9
b110010100 :
b110010100 6
b110010000 ;
b110010000 5
1"
1(
#202
0"
0(
#203
b110011000 9
b110011000 :
b110011000 6
b110010100 ;
b110010100 5
1"
1(
#204
0"
0(
#205
b110011100 9
b110011100 :
b110011100 6
b110011000 ;
b110011000 5
1"
1(
#206
0"
0(
#207
b110100000 9
b110100000 :
b110100000 6
b110011100 ;
b110011100 5
1"
1(
#208
0"
0(
#209
b110100100 9
b110100100 :
b110100100 6
b110100000 ;
b110100000 5
1"
1(
#210
0"
0(
#211
b110101000 9
b110101000 :
b110101000 6
b110100100 ;
b110100100 5
1"
1(
#212
0"
0(
#213
b110101100 9
b110101100 :
b110101100 6
b110101000 ;
b110101000 5
1"
1(
#214
0"
0(
#215
b110110000 9
b110110000 :
b110110000 6
b110101100 ;
b110101100 5
1"
1(
#216
0"
0(
#217
b110110100 9
b110110100 :
b110110100 6
b110110000 ;
b110110000 5
1"
1(
#218
0"
0(
#219
b110111000 9
b110111000 :
b110111000 6
b110110100 ;
b110110100 5
1"
1(
#220
0"
0(
#221
b110111100 9
b110111100 :
b110111100 6
b110111000 ;
b110111000 5
1"
1(
#222
0"
0(
#223
b111000000 9
b111000000 :
b111000000 6
b110111100 ;
b110111100 5
1"
1(
#224
0"
0(
#225
b111000100 9
b111000100 :
b111000100 6
b111000000 ;
b111000000 5
1"
1(
#226
0"
0(
#227
b111001000 9
b111001000 :
b111001000 6
b111000100 ;
b111000100 5
1"
1(
#228
0"
0(
#229
b111001100 9
b111001100 :
b111001100 6
b111001000 ;
b111001000 5
1"
1(
#230
0"
0(
#231
b111010000 9
b111010000 :
b111010000 6
b111001100 ;
b111001100 5
1"
1(
#232
0"
0(
#233
b111010100 9
b111010100 :
b111010100 6
b111010000 ;
b111010000 5
1"
1(
#234
0"
0(
#235
b111011000 9
b111011000 :
b111011000 6
b111010100 ;
b111010100 5
1"
1(
#236
0"
0(
#237
b111011100 9
b111011100 :
b111011100 6
b111011000 ;
b111011000 5
1"
1(
#238
0"
0(
#239
b111100000 9
b111100000 :
b111100000 6
b111011100 ;
b111011100 5
1"
1(
#240
0"
0(
#241
b111100100 9
b111100100 :
b111100100 6
b111100000 ;
b111100000 5
1"
1(
#242
0"
0(
#243
b111101000 9
b111101000 :
b111101000 6
b111100100 ;
b111100100 5
1"
1(
#244
0"
0(
#245
b111101100 9
b111101100 :
b111101100 6
b111101000 ;
b111101000 5
1"
1(
#246
0"
0(
#247
b111110000 9
b111110000 :
b111110000 6
b111101100 ;
b111101100 5
1"
1(
#248
0"
0(
#249
b111110100 9
b111110100 :
b111110100 6
b111110000 ;
b111110000 5
1"
1(
#250
0"
0(
#251
b111111000 9
b111111000 :
b111111000 6
b111110100 ;
b111110100 5
1"
1(
#252
0"
0(
#253
b111111100 9
b111111100 :
b111111100 6
b111111000 ;
b111111000 5
1"
1(
#254
0"
0(
#255
b1000000000 9
b1000000000 :
b1000000000 6
b111111100 ;
b111111100 5
1"
1(
#256
0"
0(
#257
b1000000100 9
b1000000100 :
b1000000100 6
b1000000000 ;
b1000000000 5
1"
1(
#258
0"
0(
#259
b1000001000 9
b1000001000 :
b1000001000 6
b1000000100 ;
b1000000100 5
1"
1(
#260
0"
0(
#261
b1000001100 9
b1000001100 :
b1000001100 6
b1000001000 ;
b1000001000 5
1"
1(
#262
0"
0(
#263
b1000010000 9
b1000010000 :
b1000010000 6
b1000001100 ;
b1000001100 5
1"
1(
#264
0"
0(
#265
b1000010100 9
b1000010100 :
b1000010100 6
b1000010000 ;
b1000010000 5
1"
1(
#266
0"
0(
#267
b1000011000 9
b1000011000 :
b1000011000 6
b1000010100 ;
b1000010100 5
1"
1(
#268
0"
0(
#269
b1000011100 9
b1000011100 :
b1000011100 6
b1000011000 ;
b1000011000 5
1"
1(
#270
0"
0(
#271
b1000100000 9
b1000100000 :
b1000100000 6
b1000011100 ;
b1000011100 5
1"
1(
#272
0"
0(
#273
b1000100100 9
b1000100100 :
b1000100100 6
b1000100000 ;
b1000100000 5
1"
1(
#274
0"
0(
#275
b1000101000 9
b1000101000 :
b1000101000 6
b1000100100 ;
b1000100100 5
1"
1(
#276
0"
0(
#277
b1000101100 9
b1000101100 :
b1000101100 6
b1000101000 ;
b1000101000 5
1"
1(
#278
0"
0(
#279
b1000110000 9
b1000110000 :
b1000110000 6
b1000101100 ;
b1000101100 5
1"
1(
#280
0"
0(
#281
b1000110100 9
b1000110100 :
b1000110100 6
b1000110000 ;
b1000110000 5
1"
1(
#282
0"
0(
#283
b1000111000 9
b1000111000 :
b1000111000 6
b1000110100 ;
b1000110100 5
1"
1(
#284
0"
0(
#285
b1000111100 9
b1000111100 :
b1000111100 6
b1000111000 ;
b1000111000 5
1"
1(
#286
0"
0(
#287
b1001000000 9
b1001000000 :
b1001000000 6
b1000111100 ;
b1000111100 5
1"
1(
#288
0"
0(
#289
b1001000100 9
b1001000100 :
b1001000100 6
b1001000000 ;
b1001000000 5
1"
1(
#290
0"
0(
#291
b1001001000 9
b1001001000 :
b1001001000 6
b1001000100 ;
b1001000100 5
1"
1(
#292
0"
0(
#293
b1001001100 9
b1001001100 :
b1001001100 6
b1001001000 ;
b1001001000 5
1"
1(
